fastpack/__init__.py
fastpack/__main__.py
fastpack/cli.py
fastpack/templates/.flake8
fastpack/templates/.gitignore
fastpack/templates/.pre-commit-config.yaml
fastpack/templates/README.md
fastpack/templates/pyproject.toml
fastpack-0.1.1.dist-info/METADATA
fastpack-0.1.1.dist-info/WHEEL
fastpack-0.1.1.dist-info/entry_points.txt
fastpack-0.1.1.dist-info/RECORD
