Metadata-Version: 2.3
Name: fastpack
Version: 0.1.1
Summary: Module to help initialize Python projects
Author-email: Brandon Sexton <brandon.sexton.1@outlook.com>
License-Expression: MIT
Requires-Python: >=3.9
Provides-Extra: build
Requires-Dist: build; extra == 'build'
Provides-Extra: deploy
Requires-Dist: twine; extra == 'deploy'
Provides-Extra: dev
Requires-Dist: black; extra == 'dev'
Requires-Dist: flake8; extra == 'dev'
Requires-Dist: flake8-pytest-style; extra == 'dev'
Requires-Dist: isort; extra == 'dev'
Requires-Dist: mockito; extra == 'dev'
Requires-Dist: mypy; extra == 'dev'
Requires-Dist: pre-commit; extra == 'dev'
Requires-Dist: pytest; extra == 'dev'
Requires-Dist: pytest-cov; extra == 'dev'
Provides-Extra: docs
Requires-Dist: sphinx; extra == 'docs'
Requires-Dist: sphinx-autodoc-typehints; extra == 'docs'
Requires-Dist: sphinx-markdown-builder; extra == 'docs'
Provides-Extra: test
Requires-Dist: mockito; extra == 'test'
Requires-Dist: pytest; extra == 'test'
Requires-Dist: pytest-cov; extra == 'test'
